asterix/__init__.py
asterix/core.py
asterix/test.py
asterix-0.2.3.dist-info/DESCRIPTION.rst
asterix-0.2.3.dist-info/METADATA
asterix-0.2.3.dist-info/RECORD
asterix-0.2.3.dist-info/WHEEL
asterix-0.2.3.dist-info/metadata.json
asterix-0.2.3.dist-info/top_level.txt
test/__init__.py
test/test_deps_graph.py
